setup.py
ecmc/__init__.py
ecmc/memcache_client.py
ecmc/repeat_timer.py
pyecmc.egg-info/PKG-INFO
pyecmc.egg-info/SOURCES.txt
pyecmc.egg-info/dependency_links.txt
pyecmc.egg-info/requires.txt
pyecmc.egg-info/top_level.txt
tests/__init__.py
tests/test_memcache_client.py
tests/test_repeat_timer.py