Metadata-Version: 1.0
Name: pyecmc
Version: 0.1.1
Summary: A Python module that wraps python-memcached with AWS Elasticache autodiscovery.
Home-page: https://github.com/saebyn/pyecmc
Author: John Weaver
Author-email: saebynx+pyecmc@gmail.com
License: LGPL
Keywords: aws,elasticache,memcached
Platform: any
